[{"id":7104150765621,"title":"0.9m Round Dining Table (NEW)","body_html":"<p>90x75 Black Legs Kata Gold Ceramic</p>","vendor":"Birbani","product_type":"","created_at":"2022-11-20T05:03:31-05:00","handle":"0-9m-round-dining-table-new","updated_at":"2023-10-23T22:28:22-04:00","published_at":"2022-11-20T05:03:31-05:00","template_suffix":"","published_scope":"web","tags":"Venice","status":"active","admin_graphql_api_id":"gid://shopify/Product/7104150765621","variants":[{"id":41948289597493,"product_id":7104150765621,"title":"Default Title","price":"10.00","sku":"","position":1,"inventory_policy":"deny","compare_at_price":null,"fulfillment_service":"manual","inventory_management":"shopify","option1":"Default Title","option2":null,"option3":null,"created_at":"2022-11-20T05:03:31-05:00","updated_at":"2023-10-23T22:28:22-04:00","taxable":true,"barcode":"","grams":0,"weight":0,"weight_unit":"lb","inventory_item_id":44045568639029,"inventory_quantity":10,"old_inventory_quantity":10,"requires_shipping":true,"admin_graphql_api_id":"gid://shopify/ProductVariant/41948289597493","image_id":null}],"options":[{"id":9083580514357,"product_id":7104150765621,"name":"Title","position":1,"values":["Default Title"]}],"images":[],"image":null},{"id":7104151420981,"title":"1.0m Round Dining Table","body_html":"<p>100x75 Grey/White</p>","vendor":"Birbani","product_type":"","created_at":"2022-11-20T05:03:47-05:00","handle":"1-0m-round-dining-table","updated_at":"2023-10-23T22:28:26-04:00","published_at":"2022-11-20T05:03:47-05:00","template_suffix":null,"published_scope":"web","tags":"Paris","status":"active","admin_graphql_api_id":"gid://shopify/Product/7104151420981","variants":[{"id":41948290252853,"product_id":7104151420981,"title":"Default Title","price":"0.00","sku":null,"position":1,"inventory_policy":"deny","compare_at_price":null,"fulfillment_service":"manual","inventory_management":"shopify","option1":"Default Title","option2":null,"option3":null,"created_at":"2022-11-20T05:03:47-05:00","updated_at":"2023-10-23T22:28:26-04:00","taxable":true,"barcode":null,"grams":0,"weight":0,"weight_unit":"kg","inventory_item_id":44045569294389,"inventory_quantity":0,"old_inventory_quantity":0,"requires_shipping":true,"admin_graphql_api_id":"gid://shopify/ProductVariant/41948290252853","image_id":null}],"options":[{"id":9083581169717,"product_id":7104151420981,"name":"Title","position":1,"values":["Default Title"]}],"images":[],"image":null},{"id":7104151355445,"title":"1.0m Square Dining Table","body_html":"<p>100x100x75 Grey/Mixed Brown/Black/White</p>","vendor":"Birbani","product_type":"","created_at":"2022-11-20T05:03:45-05:00","handle":"1-0m-square-dining-table","updated_at":"2023-10-23T22:28:26-04:00","published_at":"2022-11-20T05:03:45-05:00","template_suffix":null,"published_scope":"web","tags":"Lewis","status":"active","admin_graphql_api_id":"gid://shopify/Product/7104151355445","variants":[{"id":41948290187317,"product_id":7104151355445,"title":"Default Title","price":"0.00","sku":null,"position":1,"inventory_policy":"deny","compare_at_price":null,"fulfillment_service":"manual","inventory_management":"shopify","option1":"Default Title","option2":null,"option3":null,"created_at":"2022-11-20T05:03:46-05:00","updated_at":"2023-10-23T22:28:26-04:00","taxable":true,"barcode":null,"grams":0,"weight":0,"weight_unit":"lb","inventory_item_id":44045569228853,"inventory_quantity":0,"old_inventory_quantity":0,"requires_shipping":true,"admin_graphql_api_id":"gid://shopify/ProductVariant/41948290187317","image_id":null}],"options":[{"id":9083581104181,"product_id":7104151355445,"name":"Title","position":1,"values":["Default Title"]}],"images":[],"image":null},{"id":7104151322677,"title":"1.2m Dining Table","body_html":"<p>120x80x75 Grey/Mixed Brown/Black/White</p>","vendor":"Birbani","product_type":"","created_at":"2022-11-20T05:03:45-05:00","handle":"1-2m-dining-table","updated_at":"2023-10-23T22:28:25-04:00","published_at":"2022-11-20T05:03:45-05:00","template_suffix":null,"published_scope":"web","tags":"Lewis","status":"active","admin_graphql_api_id":"gid://shopify/Product/7104151322677","variants":[{"id":41948290154549,"product_id":7104151322677,"title":"Default Title","price":"0.00","sku":null,"position":1,"inventory_policy":"deny","compare_at_price":null,"fulfillment_service":"manual","inventory_management":"shopify","option1":"Default Title","option2":null,"option3":null,"created_at":"2022-11-20T05:03:45-05:00","updated_at":"2023-10-23T22:28:25-04:00","taxable":true,"barcode":null,"grams":0,"weight":0,"weight_unit":"lb","inventory_item_id":44045569196085,"inventory_quantity":0,"old_inventory_quantity":0,"requires_shipping":true,"admin_graphql_api_id":"gid://shopify/ProductVariant/41948290154549","image_id":null}],"options":[{"id":9083581071413,"product_id":7104151322677,"name":"Title","position":1,"values":["Default Title"]}],"images":[],"image":null},{"id":7104150732853,"title":"1.2m Dining Table (NEW)","body_html":"<p>120x80x75 Black Legs Kata Gold Ceramic</p>","vendor":"Birbani","product_type":"","created_at":"2022-11-20T05:03:30-05:00","handle":"1-2m-dining-table-new","updated_at":"2023-10-23T22:28:22-04:00","published_at":"2022-11-20T05:03:30-05:00","template_suffix":null,"published_scope":"web","tags":"Venice","status":"active","admin_graphql_api_id":"gid://shopify/Product/7104150732853","variants":[{"id":41948289564725,"product_id":7104150732853,"title":"Default Title","price":"0.00","sku":null,"position":1,"inventory_policy":"deny","compare_at_price":null,"fulfillment_service":"manual","inventory_management":"shopify","option1":"Default Title","option2":null,"option3":null,"created_at":"2022-11-20T05:03:30-05:00","updated_at":"2023-10-23T22:28:22-04:00","taxable":true,"barcode":null,"grams":0,"weight":0,"weight_unit":"lb","inventory_item_id":44045568606261,"inventory_quantity":0,"old_inventory_quantity":0,"requires_shipping":true,"admin_graphql_api_id":"gid://shopify/ProductVariant/41948289564725","image_id":null}],"options":[{"id":9083580481589,"product_id":7104150732853,"name":"Title","position":1,"values":["Default Title"]}],"images":[],"image":null},{"id":7104151126069,"title":"1.3m Round Dining Table","body_html":"<p>130x75 Grey/Mixed Brown/Black/White</p>","vendor":"Birbani","product_type":"","created_at":"2022-11-20T05:03:41-05:00","handle":"1-3m-round-dining-table","updated_at":"2023-10-23T22:28:24-04:00","published_at":"2022-11-20T05:03:41-05:00","template_suffix":null,"published_scope":"web","tags":"Chelsea","status":"active","admin_graphql_api_id":"gid://shopify/Product/7104151126069","variants":[{"id":41948289957941,"product_id":7104151126069,"title":"Default Title","price":"0.00","sku":null,"position":1,"inventory_policy":"deny","compare_at_price":null,"fulfillment_service":"manual","inventory_management":"shopify","option1":"Default Title","option2":null,"option3":null,"created_at":"2022-11-20T05:03:41-05:00","updated_at":"2023-10-23T22:28:24-04:00","taxable":true,"barcode":null,"grams":0,"weight":0,"weight_unit":"lb","inventory_item_id":44045568999477,"inventory_quantity":0,"old_inventory_quantity":0,"requires_shipping":true,"admin_graphql_api_id":"gid://shopify/ProductVariant/41948289957941","image_id":null}],"options":[{"id":9083580874805,"product_id":7104151126069,"name":"Title","position":1,"values":["Default Title"]}],"images":[],"image":null},{"id":7104151093301,"title":"1.5m Dining Table","body_html":"<p>150x90x75 Grey/Mixed Brown/Black/White</p>","vendor":"Birbani","product_type":"","created_at":"2022-11-20T05:03:41-05:00","handle":"1-5m-dining-table","updated_at":"2023-10-23T22:28:24-04:00","published_at":"2022-11-20T05:03:41-05:00","template_suffix":null,"published_scope":"web","tags":"Chelsea","status":"active","admin_graphql_api_id":"gid://shopify/Product/7104151093301","variants":[{"id":41948289925173,"product_id":7104151093301,"title":"Default Title","price":"0.00","sku":null,"position":1,"inventory_policy":"deny","compare_at_price":null,"fulfillment_service":"manual","inventory_management":"shopify","option1":"Default Title","option2":null,"option3":null,"created_at":"2022-11-20T05:03:41-05:00","updated_at":"2023-10-23T22:28:24-04:00","taxable":true,"barcode":null,"grams":0,"weight":0,"weight_unit":"lb","inventory_item_id":44045568966709,"inventory_quantity":0,"old_inventory_quantity":0,"requires_shipping":true,"admin_graphql_api_id":"gid://shopify/ProductVariant/41948289925173","image_id":null}],"options":[{"id":9083580842037,"product_id":7104151093301,"name":"Title","position":1,"values":["Default Title"]}],"images":[],"image":null},{"id":7104150700085,"title":"1.5m Dining Table (NEW)","body_html":"<p>150x90x75 Black Legs Kata Gold Ceramic</p>","vendor":"Birbani","product_type":"","created_at":"2022-11-20T05:03:30-05:00","handle":"1-5m-dining-table-new","updated_at":"2023-10-23T22:28:22-04:00","published_at":"2022-11-20T05:03:30-05:00","template_suffix":null,"published_scope":"web","tags":"Venice","status":"active","admin_graphql_api_id":"gid://shopify/Product/7104150700085","variants":[{"id":41948289531957,"product_id":7104150700085,"title":"Default Title","price":"0.00","sku":null,"position":1,"inventory_policy":"deny","compare_at_price":null,"fulfillment_service":"manual","inventory_management":"shopify","option1":"Default Title","option2":null,"option3":null,"created_at":"2022-11-20T05:03:30-05:00","updated_at":"2023-10-23T22:28:22-04:00","taxable":true,"barcode":null,"grams":0,"weight":0,"weight_unit":"lb","inventory_item_id":44045568573493,"inventory_quantity":0,"old_inventory_quantity":0,"requires_shipping":true,"admin_graphql_api_id":"gid://shopify/ProductVariant/41948289531957","image_id":null}],"options":[{"id":9083580448821,"product_id":7104150700085,"name":"Title","position":1,"values":["Default Title"]}],"images":[],"image":null},{"id":7104150863925,"title":"1.5m Gold Dining Table (NEW)","body_html":"<p>150x90x75 Kata Gold/Grey Ceramic</p>","vendor":"Birbani","product_type":"","created_at":"2022-11-20T05:03:37-05:00","handle":"1-5m-gold-dining-table-new","updated_at":"2023-10-23T22:28:23-04:00","published_at":"2022-11-20T05:03:37-05:00","template_suffix":null,"published_scope":"web","tags":"G-Lewis","status":"active","admin_graphql_api_id":"gid://shopify/Product/7104150863925","variants":[{"id":41948289695797,"product_id":7104150863925,"title":"Default Title","price":"0.00","sku":null,"position":1,"inventory_policy":"deny","compare_at_price":null,"fulfillment_service":"manual","inventory_management":"shopify","option1":"Default Title","option2":null,"option3":null,"created_at":"2022-11-20T05:03:37-05:00","updated_at":"2023-10-23T22:28:23-04:00","taxable":true,"barcode":null,"grams":0,"weight":0,"weight_unit":"lb","inventory_item_id":44045568737333,"inventory_quantity":0,"old_inventory_quantity":0,"requires_shipping":true,"admin_graphql_api_id":"gid://shopify/ProductVariant/41948289695797","image_id":null}],"options":[{"id":9083580612661,"product_id":7104150863925,"name":"Title","position":1,"values":["Default Title"]}],"images":[],"image":null},{"id":7104151060533,"title":"1.8m Dining Table","body_html":"<p>180x90x75 Grey/Mixed Brown/Black/White</p>","vendor":"Birbani","product_type":"","created_at":"2022-11-20T05:03:40-05:00","handle":"1-8m-dining-table","updated_at":"2023-10-23T22:28:24-04:00","published_at":"2022-11-20T05:03:40-05:00","template_suffix":null,"published_scope":"web","tags":"Chelsea","status":"active","admin_graphql_api_id":"gid://shopify/Product/7104151060533","variants":[{"id":41948289892405,"product_id":7104151060533,"title":"Default Title","price":"0.00","sku":null,"position":1,"inventory_policy":"deny","compare_at_price":null,"fulfillment_service":"manual","inventory_management":"shopify","option1":"Default Title","option2":null,"option3":null,"created_at":"2022-11-20T05:03:40-05:00","updated_at":"2023-10-23T22:28:24-04:00","taxable":true,"barcode":null,"grams":0,"weight":0,"weight_unit":"lb","inventory_item_id":44045568933941,"inventory_quantity":0,"old_inventory_quantity":0,"requires_shipping":true,"admin_graphql_api_id":"gid://shopify/ProductVariant/41948289892405","image_id":null}],"options":[{"id":9083580809269,"product_id":7104151060533,"name":"Title","position":1,"values":["Default Title"]}],"images":[],"image":null},{"id":7104150994997,"title":"1.8m Dining Table (NEW)","body_html":"<p>180x90x75 Kata Gold/Grey Ceramic</p>","vendor":"Birbani","product_type":"","created_at":"2022-11-20T05:03:39-05:00","handle":"1-8m-dining-table-new","updated_at":"2023-10-23T22:28:24-04:00","published_at":"2022-11-20T05:03:39-05:00","template_suffix":null,"published_scope":"web","tags":"Barcelona","status":"active","admin_graphql_api_id":"gid://shopify/Product/7104150994997","variants":[{"id":41948289826869,"product_id":7104150994997,"title":"Default Title","price":"0.00","sku":null,"position":1,"inventory_policy":"deny","compare_at_price":null,"fulfillment_service":"manual","inventory_management":"shopify","option1":"Default Title","option2":null,"option3":null,"created_at":"2022-11-20T05:03:39-05:00","updated_at":"2023-10-23T22:28:24-04:00","taxable":true,"barcode":null,"grams":0,"weight":0,"weight_unit":"lb","inventory_item_id":44045568868405,"inventory_quantity":0,"old_inventory_quantity":0,"requires_shipping":true,"admin_graphql_api_id":"gid://shopify/ProductVariant/41948289826869","image_id":null}],"options":[{"id":9083580743733,"product_id":7104150994997,"name":"Title","position":1,"values":["Default Title"]}],"images":[],"image":null},{"id":7104150831157,"title":"1.8m Gold Dining Table (NEW)","body_html":"<p>180x90x75 Kata Gold/Grey Ceramic</p>","vendor":"Birbani","product_type":"","created_at":"2022-11-20T05:03:34-05:00","handle":"1-8m-gold-dining-table-new","updated_at":"2023-10-23T22:28:23-04:00","published_at":"2022-11-20T05:03:34-05:00","template_suffix":null,"published_scope":"web","tags":"G-Lewis","status":"active","admin_graphql_api_id":"gid://shopify/Product/7104150831157","variants":[{"id":41948289663029,"product_id":7104150831157,"title":"Default Title","price":"0.00","sku":null,"position":1,"inventory_policy":"deny","compare_at_price":null,"fulfillment_service":"manual","inventory_management":"shopify","option1":"Default Title","option2":null,"option3":null,"created_at":"2022-11-20T05:03:34-05:00","updated_at":"2023-10-23T22:28:23-04:00","taxable":true,"barcode":null,"grams":0,"weight":0,"weight_unit":"lb","inventory_item_id":44045568704565,"inventory_quantity":0,"old_inventory_quantity":0,"requires_shipping":true,"admin_graphql_api_id":"gid://shopify/ProductVariant/41948289663029","image_id":null}],"options":[{"id":9083580579893,"product_id":7104150831157,"name":"Title","position":1,"values":["Default Title"]}],"images":[],"image":null},{"id":7104152698933,"title":"2 Door Wardrobe","body_html":"<p>100x55x197</p>","vendor":"Birbani","product_type":"","created_at":"2022-11-20T05:04:10-05:00","handle":"2-door-wardrobe","updated_at":"2023-10-23T22:28:34-04:00","published_at":"2022-11-20T05:04:10-05:00","template_suffix":null,"published_scope":"web","tags":"Milan","status":"active","admin_graphql_api_id":"gid://shopify/Product/7104152698933","variants":[{"id":41948291530805,"product_id":7104152698933,"title":"Default Title","price":"0.00","sku":null,"position":1,"inventory_policy":"deny","compare_at_price":null,"fulfillment_service":"manual","inventory_management":"shopify","option1":"Default Title","option2":null,"option3":null,"created_at":"2022-11-20T05:04:10-05:00","updated_at":"2023-10-23T22:28:34-04:00","taxable":true,"barcode":null,"grams":0,"weight":0,"weight_unit":"kg","inventory_item_id":44045570572341,"inventory_quantity":0,"old_inventory_quantity":0,"requires_shipping":true,"admin_graphql_api_id":"gid://shopify/ProductVariant/41948291530805","image_id":null}],"options":[{"id":9083582447669,"product_id":7104152698933,"name":"Title","position":1,"values":["Default Title"]}],"images":[],"image":null},{"id":7104152731701,"title":"2 Drawer Bedside","body_html":"<p>45x40x54</p>","vendor":"Birbani","product_type":"","created_at":"2022-11-20T05:04:10-05:00","handle":"2-drawer-bedside","updated_at":"2023-10-23T22:28:34-04:00","published_at":"2022-11-20T05:04:10-05:00","template_suffix":null,"published_scope":"web","tags":"Milan","status":"active","admin_graphql_api_id":"gid://shopify/Product/7104152731701","variants":[{"id":41948291563573,"product_id":7104152731701,"title":"Default Title","price":"0.00","sku":null,"position":1,"inventory_policy":"deny","compare_at_price":null,"fulfillment_service":"manual","inventory_management":"shopify","option1":"Default Title","option2":null,"option3":null,"created_at":"2022-11-20T05:04:10-05:00","updated_at":"2023-10-23T22:28:34-04:00","taxable":true,"barcode":null,"grams":0,"weight":0,"weight_unit":"kg","inventory_item_id":44045570605109,"inventory_quantity":0,"old_inventory_quantity":0,"requires_shipping":true,"admin_graphql_api_id":"gid://shopify/ProductVariant/41948291563573","image_id":null}],"options":[{"id":9083582480437,"product_id":7104152731701,"name":"Title","position":1,"values":["Default Title"]}],"images":[],"image":null},{"id":7104152797237,"title":"2+3 Chest","body_html":"<p>80x40x95</p>","vendor":"Birbani","product_type":"","created_at":"2022-11-20T05:04:11-05:00","handle":"2-3-chest","updated_at":"2023-10-23T22:28:34-04:00","published_at":"2022-11-20T05:04:11-05:00","template_suffix":null,"published_scope":"web","tags":"Milan","status":"active","admin_graphql_api_id":"gid://shopify/Product/7104152797237","variants":[{"id":41948291629109,"product_id":7104152797237,"title":"Default Title","price":"0.00","sku":null,"position":1,"inventory_policy":"deny","compare_at_price":null,"fulfillment_service":"manual","inventory_management":"shopify","option1":"Default Title","option2":null,"option3":null,"created_at":"2022-11-20T05:04:11-05:00","updated_at":"2023-10-23T22:28:34-04:00","taxable":true,"barcode":null,"grams":0,"weight":0,"weight_unit":"kg","inventory_item_id":44045570670645,"inventory_quantity":0,"old_inventory_quantity":0,"requires_shipping":true,"admin_graphql_api_id":"gid://shopify/ProductVariant/41948291629109","image_id":null}],"options":[{"id":9083582545973,"product_id":7104152797237,"name":"Title","position":1,"values":["Default Title"]}],"images":[],"image":null},{"id":7104151027765,"title":"2.0m Dining Table","body_html":"<p>200x100x75 Grey/Black/White</p>","vendor":"Birbani","product_type":"","created_at":"2022-11-20T05:03:40-05:00","handle":"2-0m-dining-table","updated_at":"2023-10-23T22:28:24-04:00","published_at":"2022-11-20T05:03:40-05:00","template_suffix":null,"published_scope":"web","tags":"Chelsea","status":"active","admin_graphql_api_id":"gid://shopify/Product/7104151027765","variants":[{"id":41948289859637,"product_id":7104151027765,"title":"Default Title","price":"0.00","sku":null,"position":1,"inventory_policy":"deny","compare_at_price":null,"fulfillment_service":"manual","inventory_management":"shopify","option1":"Default Title","option2":null,"option3":null,"created_at":"2022-11-20T05:03:40-05:00","updated_at":"2023-10-23T22:28:24-04:00","taxable":true,"barcode":null,"grams":0,"weight":0,"weight_unit":"lb","inventory_item_id":44045568901173,"inventory_quantity":0,"old_inventory_quantity":0,"requires_shipping":true,"admin_graphql_api_id":"gid://shopify/ProductVariant/41948289859637","image_id":null}],"options":[{"id":9083580776501,"product_id":7104151027765,"name":"Title","position":1,"values":["Default Title"]}],"images":[],"image":null},{"id":7104152764469,"title":"3 Drawer Chest","body_html":"<p>80x40x74</p>","vendor":"Birbani","product_type":"","created_at":"2022-11-20T05:04:11-05:00","handle":"3-drawer-chest","updated_at":"2023-10-23T22:28:34-04:00","published_at":"2022-11-20T05:04:11-05:00","template_suffix":null,"published_scope":"web","tags":"Milan","status":"active","admin_graphql_api_id":"gid://shopify/Product/7104152764469","variants":[{"id":41948291596341,"product_id":7104152764469,"title":"Default Title","price":"0.00","sku":null,"position":1,"inventory_policy":"deny","compare_at_price":null,"fulfillment_service":"manual","inventory_management":"shopify","option1":"Default Title","option2":null,"option3":null,"created_at":"2022-11-20T05:04:11-05:00","updated_at":"2023-10-23T22:28:34-04:00","taxable":true,"barcode":null,"grams":0,"weight":0,"weight_unit":"kg","inventory_item_id":44045570637877,"inventory_quantity":0,"old_inventory_quantity":0,"requires_shipping":true,"admin_graphql_api_id":"gid://shopify/ProductVariant/41948291596341","image_id":null}],"options":[{"id":9083582513205,"product_id":7104152764469,"name":"Title","position":1,"values":["Default Title"]}],"images":[],"image":null},{"id":7104152371253,"title":"4'6 ft Bed","body_html":"<p>145x203x105</p>","vendor":"Birbani","product_type":"","created_at":"2022-11-20T05:04:04-05:00","handle":"46-ft-bed","updated_at":"2023-10-23T22:28:32-04:00","published_at":"2022-11-20T05:04:04-05:00","template_suffix":null,"published_scope":"web","tags":"Torino/Lucca","status":"active","admin_graphql_api_id":"gid://shopify/Product/7104152371253","variants":[{"id":41948291203125,"product_id":7104152371253,"title":"Default Title","price":"0.00","sku":null,"position":1,"inventory_policy":"deny","compare_at_price":null,"fulfillment_service":"manual","inventory_management":"shopify","option1":"Default Title","option2":null,"option3":null,"created_at":"2022-11-20T05:04:04-05:00","updated_at":"2023-10-23T22:28:32-04:00","taxable":true,"barcode":null,"grams":0,"weight":0,"weight_unit":"kg","inventory_item_id":44045570244661,"inventory_quantity":0,"old_inventory_quantity":0,"requires_shipping":true,"admin_graphql_api_id":"gid://shopify/ProductVariant/41948291203125","image_id":null}],"options":[{"id":9083582119989,"product_id":7104152371253,"name":"Title","position":1,"values":["Default Title"]}],"images":[],"image":null},{"id":7104152404021,"title":"5'ft Bed","body_html":"<p>160x217x105</p>","vendor":"Birbani","product_type":"","created_at":"2022-11-20T05:04:04-05:00","handle":"5ft-bed","updated_at":"2023-10-23T22:28:32-04:00","published_at":"2022-11-20T05:04:04-05:00","template_suffix":null,"published_scope":"web","tags":"Torino/Lucca","status":"active","admin_graphql_api_id":"gid://shopify/Product/7104152404021","variants":[{"id":41948291235893,"product_id":7104152404021,"title":"Default Title","price":"0.00","sku":null,"position":1,"inventory_policy":"deny","compare_at_price":null,"fulfillment_service":"manual","inventory_management":"shopify","option1":"Default Title","option2":null,"option3":null,"created_at":"2022-11-20T05:04:05-05:00","updated_at":"2023-10-23T22:28:32-04:00","taxable":true,"barcode":null,"grams":0,"weight":0,"weight_unit":"kg","inventory_item_id":44045570277429,"inventory_quantity":0,"old_inventory_quantity":0,"requires_shipping":true,"admin_graphql_api_id":"gid://shopify/ProductVariant/41948291235893","image_id":null}],"options":[{"id":9083582152757,"product_id":7104152404021,"name":"Title","position":1,"values":["Default Title"]}],"images":[],"image":null},{"id":7104149848117,"title":"Alice Chair with chrome legs (KD)","body_html":"<p>59x46x105 Crushed Silver/Grey/Crushed Black</p>","vendor":"Birbani","product_type":"","created_at":"2022-11-20T05:03:14-05:00","handle":"alice-chair-with-chrome-legs-kd","updated_at":"2023-10-23T22:28:16-04:00","published_at":"2022-11-20T05:03:14-05:00","template_suffix":null,"published_scope":"web","tags":"Chair","status":"active","admin_graphql_api_id":"gid://shopify/Product/7104149848117","variants":[{"id":41948288679989,"product_id":7104149848117,"title":"Default Title","price":"0.00","sku":null,"position":1,"inventory_policy":"deny","compare_at_price":null,"fulfillment_service":"manual","inventory_management":"shopify","option1":"Default Title","option2":null,"option3":null,"created_at":"2022-11-20T05:03:14-05:00","updated_at":"2023-10-23T22:28:16-04:00","taxable":true,"barcode":null,"grams":0,"weight":0,"weight_unit":"lb","inventory_item_id":44045567721525,"inventory_quantity":0,"old_inventory_quantity":0,"requires_shipping":true,"admin_graphql_api_id":"gid://shopify/ProductVariant/41948288679989","image_id":null}],"options":[{"id":9083579596853,"product_id":7104149848117,"name":"Title","position":1,"values":["Default Title"]}],"images":[],"image":null},{"id":7104152436789,"title":"Bedside 1 Drawer","body_html":"<p>44x37x62</p>","vendor":"Birbani","product_type":"","created_at":"2022-11-20T05:04:05-05:00","handle":"bedside-1-drawer","updated_at":"2023-10-23T22:28:32-04:00","published_at":"2022-11-20T05:04:05-05:00","template_suffix":null,"published_scope":"web","tags":"Torino/Lucca","status":"active","admin_graphql_api_id":"gid://shopify/Product/7104152436789","variants":[{"id":41948291268661,"product_id":7104152436789,"title":"Default Title","price":"0.00","sku":null,"position":1,"inventory_policy":"deny","compare_at_price":null,"fulfillment_service":"manual","inventory_management":"shopify","option1":"Default Title","option2":null,"option3":null,"created_at":"2022-11-20T05:04:05-05:00","updated_at":"2023-10-23T22:28:32-04:00","taxable":true,"barcode":null,"grams":0,"weight":0,"weight_unit":"kg","inventory_item_id":44045570310197,"inventory_quantity":0,"old_inventory_quantity":0,"requires_shipping":true,"admin_graphql_api_id":"gid://shopify/ProductVariant/41948291268661","image_id":null}],"options":[{"id":9083582185525,"product_id":7104152436789,"name":"Title","position":1,"values":["Default Title"]}],"images":[],"image":null},{"id":7104152469557,"title":"Bedside 3 Drawers","body_html":"<p>47x37x62</p>","vendor":"Birbani","product_type":"","created_at":"2022-11-20T05:04:06-05:00","handle":"bedside-3-drawers","updated_at":"2023-10-23T22:28:32-04:00","published_at":"2022-11-20T05:04:06-05:00","template_suffix":null,"published_scope":"web","tags":"Torino/Lucca","status":"active","admin_graphql_api_id":"gid://shopify/Product/7104152469557","variants":[{"id":41948291301429,"product_id":7104152469557,"title":"Default Title","price":"0.00","sku":null,"position":1,"inventory_policy":"deny","compare_at_price":null,"fulfillment_service":"manual","inventory_management":"shopify","option1":"Default Title","option2":null,"option3":null,"created_at":"2022-11-20T05:04:06-05:00","updated_at":"2023-10-23T22:28:32-04:00","taxable":true,"barcode":null,"grams":0,"weight":0,"weight_unit":"kg","inventory_item_id":44045570342965,"inventory_quantity":0,"old_inventory_quantity":0,"requires_shipping":true,"admin_graphql_api_id":"gid://shopify/ProductVariant/41948291301429","image_id":null}],"options":[{"id":9083582218293,"product_id":7104152469557,"name":"Title","position":1,"values":["Default Title"]}],"images":[],"image":null},{"id":7104151617589,"title":"Berry Chair (Beige/Mixed Brown/Grey) Fabric","body_html":"<p>47x65x106</p>","vendor":"Birbani","product_type":"","created_at":"2022-11-20T05:03:51-05:00","handle":"berry-chair-beige-mixed-brown-grey-fabric","updated_at":"2023-10-23T22:28:27-04:00","published_at":"2022-11-20T05:03:51-05:00","template_suffix":null,"published_scope":"web","tags":"Chair","status":"active","admin_graphql_api_id":"gid://shopify/Product/7104151617589","variants":[{"id":41948290449461,"product_id":7104151617589,"title":"Default Title","price":"0.00","sku":null,"position":1,"inventory_policy":"deny","compare_at_price":null,"fulfillment_service":"manual","inventory_management":"shopify","option1":"Default Title","option2":null,"option3":null,"created_at":"2022-11-20T05:03:51-05:00","updated_at":"2023-10-23T22:28:27-04:00","taxable":true,"barcode":null,"grams":0,"weight":0,"weight_unit":"kg","inventory_item_id":44045569490997,"inventory_quantity":0,"old_inventory_quantity":0,"requires_shipping":true,"admin_graphql_api_id":"gid://shopify/ProductVariant/41948290449461","image_id":null}],"options":[{"id":9083581366325,"product_id":7104151617589,"name":"Title","position":1,"values":["Default Title"]}],"images":[],"image":null},{"id":7104152862773,"title":"Bookcase","body_html":"<p>110x33x155</p>","vendor":"Birbani","product_type":"","created_at":"2022-11-20T05:04:12-05:00","handle":"bookcase","updated_at":"2023-10-23T22:28:35-04:00","published_at":"2022-11-20T05:04:12-05:00","template_suffix":null,"published_scope":"web","tags":"Milan","status":"active","admin_graphql_api_id":"gid://shopify/Product/7104152862773","variants":[{"id":41948291694645,"product_id":7104152862773,"title":"Default Title","price":"0.00","sku":null,"position":1,"inventory_policy":"deny","compare_at_price":null,"fulfillment_service":"manual","inventory_management":"shopify","option1":"Default Title","option2":null,"option3":null,"created_at":"2022-11-20T05:04:13-05:00","updated_at":"2023-10-23T22:28:35-04:00","taxable":true,"barcode":null,"grams":0,"weight":0,"weight_unit":"kg","inventory_item_id":44045570736181,"inventory_quantity":0,"old_inventory_quantity":0,"requires_shipping":true,"admin_graphql_api_id":"gid://shopify/ProductVariant/41948291694645","image_id":null}],"options":[{"id":9083582611509,"product_id":7104152862773,"name":"Title","position":1,"values":["Default Title"]}],"images":[],"image":null},{"id":7104150667317,"title":"Chelsea Bench 130","body_html":"<p>130x48x50 Grey</p>","vendor":"Birbani","product_type":"","created_at":"2022-11-20T05:03:29-05:00","handle":"chelsea-bench-130","updated_at":"2023-10-23T22:28:21-04:00","published_at":"2022-11-20T05:03:29-05:00","template_suffix":null,"published_scope":"web","tags":"Bench","status":"active","admin_graphql_api_id":"gid://shopify/Product/7104150667317","variants":[{"id":41948289499189,"product_id":7104150667317,"title":"Default Title","price":"0.00","sku":null,"position":1,"inventory_policy":"deny","compare_at_price":null,"fulfillment_service":"manual","inventory_management":"shopify","option1":"Default Title","option2":null,"option3":null,"created_at":"2022-11-20T05:03:29-05:00","updated_at":"2023-10-23T22:28:21-04:00","taxable":true,"barcode":null,"grams":0,"weight":0,"weight_unit":"kg","inventory_item_id":44045568540725,"inventory_quantity":0,"old_inventory_quantity":0,"requires_shipping":true,"admin_graphql_api_id":"gid://shopify/ProductVariant/41948289499189","image_id":null}],"options":[{"id":9083580416053,"product_id":7104150667317,"name":"Title","position":1,"values":["Default Title"]}],"images":[],"image":null},{"id":7104149880885,"title":"Chelsea Chair ringer (and 01 lion) with chrome legs (KD)","body_html":"<p>62x60x96 Dark Grey/Cream/Black</p>","vendor":"Birbani","product_type":"","created_at":"2022-11-20T05:03:15-05:00","handle":"chelsea-chair-ringer-and-01-lion-with-chrome-legs-kd","updated_at":"2023-10-23T22:28:17-04:00","published_at":"2022-11-20T05:03:15-05:00","template_suffix":null,"published_scope":"web","tags":"Chair","status":"active","admin_graphql_api_id":"gid://shopify/Product/7104149880885","variants":[{"id":41948288712757,"product_id":7104149880885,"title":"Default Title","price":"0.00","sku":null,"position":1,"inventory_policy":"deny","compare_at_price":null,"fulfillment_service":"manual","inventory_management":"shopify","option1":"Default Title","option2":null,"option3":null,"created_at":"2022-11-20T05:03:15-05:00","updated_at":"2023-10-23T22:28:17-04:00","taxable":true,"barcode":null,"grams":0,"weight":0,"weight_unit":"lb","inventory_item_id":44045567754293,"inventory_quantity":0,"old_inventory_quantity":0,"requires_shipping":true,"admin_graphql_api_id":"gid://shopify/ProductVariant/41948288712757","image_id":null}],"options":[{"id":9083579629621,"product_id":7104149880885,"name":"Title","position":1,"values":["Default Title"]}],"images":[],"image":null},{"id":7104150405173,"title":"Chelsea ring (and 01 lion) Bar Stool","body_html":"<p>54x48x102 Dark Grey</p>","vendor":"Birbani","product_type":"","created_at":"2022-11-20T05:03:24-05:00","handle":"chelsea-ring-and-01-lion-bar-stool","updated_at":"2023-10-23T22:28:20-04:00","published_at":"2022-11-20T05:03:24-05:00","template_suffix":null,"published_scope":"web","tags":"Stool","status":"active","admin_graphql_api_id":"gid://shopify/Product/7104150405173","variants":[{"id":41948289237045,"product_id":7104150405173,"title":"Default Title","price":"0.00","sku":null,"position":1,"inventory_policy":"deny","compare_at_price":null,"fulfillment_service":"manual","inventory_management":"shopify","option1":"Default Title","option2":null,"option3":null,"created_at":"2022-11-20T05:03:24-05:00","updated_at":"2023-10-23T22:28:20-04:00","taxable":true,"barcode":null,"grams":0,"weight":0,"weight_unit":"lb","inventory_item_id":44045568278581,"inventory_quantity":0,"old_inventory_quantity":0,"requires_shipping":true,"admin_graphql_api_id":"gid://shopify/ProductVariant/41948289237045","image_id":null}],"options":[{"id":9083580153909,"product_id":7104150405173,"name":"Title","position":1,"values":["Default Title"]}],"images":[],"image":null},{"id":7104152502325,"title":"Chest 2 Over 3","body_html":"<p>85x40x96</p>","vendor":"Birbani","product_type":"","created_at":"2022-11-20T05:04:06-05:00","handle":"chest-2-over-3","updated_at":"2023-10-23T22:28:32-04:00","published_at":"2022-11-20T05:04:06-05:00","template_suffix":null,"published_scope":"web","tags":"Torino/Lucca","status":"active","admin_graphql_api_id":"gid://shopify/Product/7104152502325","variants":[{"id":41948291334197,"product_id":7104152502325,"title":"Default Title","price":"0.00","sku":null,"position":1,"inventory_policy":"deny","compare_at_price":null,"fulfillment_service":"manual","inventory_management":"shopify","option1":"Default Title","option2":null,"option3":null,"created_at":"2022-11-20T05:04:06-05:00","updated_at":"2023-10-23T22:28:32-04:00","taxable":true,"barcode":null,"grams":0,"weight":0,"weight_unit":"kg","inventory_item_id":44045570375733,"inventory_quantity":0,"old_inventory_quantity":0,"requires_shipping":true,"admin_graphql_api_id":"gid://shopify/ProductVariant/41948291334197","image_id":null}],"options":[{"id":9083582251061,"product_id":7104152502325,"name":"Title","position":1,"values":["Default Title"]}],"images":[],"image":null},{"id":7104152535093,"title":"Chest 6 Drawers","body_html":"<p>128x40x78</p>","vendor":"Birbani","product_type":"","created_at":"2022-11-20T05:04:07-05:00","handle":"chest-6-drawers","updated_at":"2023-10-23T22:28:33-04:00","published_at":"2022-11-20T05:04:07-05:00","template_suffix":null,"published_scope":"web","tags":"Torino/Lucca","status":"active","admin_graphql_api_id":"gid://shopify/Product/7104152535093","variants":[{"id":41948291366965,"product_id":7104152535093,"title":"Default Title","price":"0.00","sku":null,"position":1,"inventory_policy":"deny","compare_at_price":null,"fulfillment_service":"manual","inventory_management":"shopify","option1":"Default Title","option2":null,"option3":null,"created_at":"2022-11-20T05:04:07-05:00","updated_at":"2023-10-23T22:28:33-04:00","taxable":true,"barcode":null,"grams":0,"weight":0,"weight_unit":"kg","inventory_item_id":44045570408501,"inventory_quantity":0,"old_inventory_quantity":0,"requires_shipping":true,"admin_graphql_api_id":"gid://shopify/ProductVariant/41948291366965","image_id":null}],"options":[{"id":9083582283829,"product_id":7104152535093,"name":"Title","position":1,"values":["Default Title"]}],"images":[],"image":null},{"id":7104151158837,"title":"Coffee Table","body_html":"<p>120x60x45 Grey/Mixed Brown/Black/White</p>","vendor":"Birbani","product_type":"","created_at":"2022-11-20T05:03:42-05:00","handle":"coffee-table","updated_at":"2023-10-23T22:28:24-04:00","published_at":"2022-11-20T05:03:42-05:00","template_suffix":null,"published_scope":"web","tags":"Chelsea","status":"active","admin_graphql_api_id":"gid://shopify/Product/7104151158837","variants":[{"id":41948289990709,"product_id":7104151158837,"title":"Default Title","price":"0.00","sku":null,"position":1,"inventory_policy":"deny","compare_at_price":null,"fulfillment_service":"manual","inventory_management":"shopify","option1":"Default Title","option2":null,"option3":null,"created_at":"2022-11-20T05:03:42-05:00","updated_at":"2023-10-23T22:28:24-04:00","taxable":true,"barcode":null,"grams":0,"weight":0,"weight_unit":"lb","inventory_item_id":44045569032245,"inventory_quantity":0,"old_inventory_quantity":0,"requires_shipping":true,"admin_graphql_api_id":"gid://shopify/ProductVariant/41948289990709","image_id":null}],"options":[{"id":9083580907573,"product_id":7104151158837,"name":"Title","position":1,"values":["Default Title"]}],"images":[],"image":null},{"id":7104150896693,"title":"Coffee Table (NEW)","body_html":"<p>120x60x45 Kata Gold Ceramic</p>","vendor":"Birbani","product_type":"","created_at":"2022-11-20T05:03:37-05:00","handle":"coffee-table-new","updated_at":"2023-10-23T22:28:23-04:00","published_at":"2022-11-20T05:03:37-05:00","template_suffix":null,"published_scope":"web","tags":"G-Lewis","status":"active","admin_graphql_api_id":"gid://shopify/Product/7104150896693","variants":[{"id":41948289728565,"product_id":7104150896693,"title":"Default Title","price":"0.00","sku":null,"position":1,"inventory_policy":"deny","compare_at_price":null,"fulfillment_service":"manual","inventory_management":"shopify","option1":"Default Title","option2":null,"option3":null,"created_at":"2022-11-20T05:03:37-05:00","updated_at":"2023-10-23T22:28:23-04:00","taxable":true,"barcode":null,"grams":0,"weight":0,"weight_unit":"lb","inventory_item_id":44045568770101,"inventory_quantity":0,"old_inventory_quantity":0,"requires_shipping":true,"admin_graphql_api_id":"gid://shopify/ProductVariant/41948289728565","image_id":null}],"options":[{"id":9083580645429,"product_id":7104150896693,"name":"Title","position":1,"values":["Default Title"]}],"images":[],"image":null},{"id":7104152010805,"title":"Coffee Table With Drawers","body_html":"<p>90x55x50</p>","vendor":"Birbani","product_type":"","created_at":"2022-11-20T05:03:58-05:00","handle":"coffee-table-with-drawers","updated_at":"2023-10-23T22:28:30-04:00","published_at":"2022-11-20T05:03:58-05:00","template_suffix":null,"published_scope":"web","tags":"Torino/Lucca","status":"active","admin_graphql_api_id":"gid://shopify/Product/7104152010805","variants":[{"id":41948290842677,"product_id":7104152010805,"title":"Default Title","price":"0.00","sku":null,"position":1,"inventory_policy":"deny","compare_at_price":null,"fulfillment_service":"manual","inventory_management":"shopify","option1":"Default Title","option2":null,"option3":null,"created_at":"2022-11-20T05:03:58-05:00","updated_at":"2023-10-23T22:28:30-04:00","taxable":true,"barcode":null,"grams":0,"weight":0,"weight_unit":"kg","inventory_item_id":44045569884213,"inventory_quantity":0,"old_inventory_quantity":0,"requires_shipping":true,"admin_graphql_api_id":"gid://shopify/ProductVariant/41948290842677","image_id":null}],"options":[{"id":9083581759541,"product_id":7104152010805,"name":"Title","position":1,"values":["Default Title"]}],"images":[],"image":null},{"id":7104151191605,"title":"Console Table","body_html":"<p>120x40x75 Grey/Mixed Brown/Black/White</p>","vendor":"Birbani","product_type":"","created_at":"2022-11-20T05:03:42-05:00","handle":"console-table","updated_at":"2023-10-23T22:28:25-04:00","published_at":"2022-11-20T05:03:42-05:00","template_suffix":null,"published_scope":"web","tags":"Chelsea","status":"active","admin_graphql_api_id":"gid://shopify/Product/7104151191605","variants":[{"id":41948290023477,"product_id":7104151191605,"title":"Default Title","price":"0.00","sku":null,"position":1,"inventory_policy":"deny","compare_at_price":null,"fulfillment_service":"manual","inventory_management":"shopify","option1":"Default Title","option2":null,"option3":null,"created_at":"2022-11-20T05:03:43-05:00","updated_at":"2023-10-23T22:28:25-04:00","taxable":true,"barcode":null,"grams":0,"weight":0,"weight_unit":"lb","inventory_item_id":44045569065013,"inventory_quantity":0,"old_inventory_quantity":0,"requires_shipping":true,"admin_graphql_api_id":"gid://shopify/ProductVariant/41948290023477","image_id":null}],"options":[{"id":9083580940341,"product_id":7104151191605,"name":"Title","position":1,"values":["Default Title"]}],"images":[],"image":null},{"id":7104152109109,"title":"Console Table 2 Drawers","body_html":"<p>85x34x70</p>","vendor":"Birbani","product_type":"","created_at":"2022-11-20T05:03:59-05:00","handle":"console-table-2-drawers","updated_at":"2023-10-23T22:28:30-04:00","published_at":"2022-11-20T05:03:59-05:00","template_suffix":null,"published_scope":"web","tags":"Torino/Lucca","status":"active","admin_graphql_api_id":"gid://shopify/Product/7104152109109","variants":[{"id":41948290940981,"product_id":7104152109109,"title":"Default Title","price":"0.00","sku":null,"position":1,"inventory_policy":"deny","compare_at_price":null,"fulfillment_service":"manual","inventory_management":"shopify","option1":"Default Title","option2":null,"option3":null,"created_at":"2022-11-20T05:03:59-05:00","updated_at":"2023-10-23T22:28:30-04:00","taxable":true,"barcode":null,"grams":0,"weight":0,"weight_unit":"kg","inventory_item_id":44045569982517,"inventory_quantity":0,"old_inventory_quantity":0,"requires_shipping":true,"admin_graphql_api_id":"gid://shopify/ProductVariant/41948290940981","image_id":null}],"options":[{"id":9083581857845,"product_id":7104152109109,"name":"Title","position":1,"values":["Default Title"]}],"images":[],"image":null},{"id":7104152141877,"title":"Corner TV Unit","body_html":"<p>80x40x65</p>","vendor":"Birbani","product_type":"","created_at":"2022-11-20T05:04:00-05:00","handle":"corner-tv-unit","updated_at":"2023-10-23T22:28:30-04:00","published_at":"2022-11-20T05:04:00-05:00","template_suffix":null,"published_scope":"web","tags":"Torino/Lucca","status":"active","admin_graphql_api_id":"gid://shopify/Product/7104152141877","variants":[{"id":41948290973749,"product_id":7104152141877,"title":"Default Title","price":"0.00","sku":null,"position":1,"inventory_policy":"deny","compare_at_price":null,"fulfillment_service":"manual","inventory_management":"shopify","option1":"Default Title","option2":null,"option3":null,"created_at":"2022-11-20T05:04:00-05:00","updated_at":"2023-10-23T22:28:30-04:00","taxable":true,"barcode":null,"grams":0,"weight":0,"weight_unit":"kg","inventory_item_id":44045570015285,"inventory_quantity":0,"old_inventory_quantity":0,"requires_shipping":true,"admin_graphql_api_id":"gid://shopify/ProductVariant/41948290973749","image_id":null}],"options":[{"id":9083581890613,"product_id":7104152141877,"name":"Title","position":1,"values":["Default Title"]}],"images":[],"image":null},{"id":7104152338485,"title":"Display Cabinet","body_html":"<p>36x85x180</p>","vendor":"Birbani","product_type":"","created_at":"2022-11-20T05:04:03-05:00","handle":"display-cabinet","updated_at":"2023-10-23T22:28:32-04:00","published_at":"2022-11-20T05:04:03-05:00","template_suffix":null,"published_scope":"web","tags":"Torino/Lucca","status":"active","admin_graphql_api_id":"gid://shopify/Product/7104152338485","variants":[{"id":41948291170357,"product_id":7104152338485,"title":"Default Title","price":"0.00","sku":null,"position":1,"inventory_policy":"deny","compare_at_price":null,"fulfillment_service":"manual","inventory_management":"shopify","option1":"Default Title","option2":null,"option3":null,"created_at":"2022-11-20T05:04:03-05:00","updated_at":"2023-10-23T22:28:32-04:00","taxable":true,"barcode":null,"grams":0,"weight":0,"weight_unit":"kg","inventory_item_id":44045570211893,"inventory_quantity":0,"old_inventory_quantity":0,"requires_shipping":true,"admin_graphql_api_id":"gid://shopify/ProductVariant/41948291170357","image_id":null}],"options":[{"id":9083582087221,"product_id":7104152338485,"name":"Title","position":1,"values":["Default Title"]}],"images":[],"image":null},{"id":7104152666165,"title":"Dressing table","body_html":"<p>107x44x75</p>","vendor":"Birbani","product_type":"","created_at":"2022-11-20T05:04:09-05:00","handle":"dressing-table","updated_at":"2023-10-23T22:28:33-04:00","published_at":"2022-11-20T05:04:09-05:00","template_suffix":null,"published_scope":"web","tags":"Torino","status":"active","admin_graphql_api_id":"gid://shopify/Product/7104152666165","variants":[{"id":41948291498037,"product_id":7104152666165,"title":"Default Title","price":"0.00","sku":null,"position":1,"inventory_policy":"deny","compare_at_price":null,"fulfillment_service":"manual","inventory_management":"shopify","option1":"Default Title","option2":null,"option3":null,"created_at":"2022-11-20T05:04:09-05:00","updated_at":"2023-10-23T22:28:33-04:00","taxable":true,"barcode":null,"grams":0,"weight":0,"weight_unit":"kg","inventory_item_id":44045570539573,"inventory_quantity":0,"old_inventory_quantity":0,"requires_shipping":true,"admin_graphql_api_id":"gid://shopify/ProductVariant/41948291498037","image_id":null}],"options":[{"id":9083582414901,"product_id":7104152666165,"name":"Title","position":1,"values":["Default Title"]}],"images":[],"image":null},{"id":7104150339637,"title":"G-Roma Chair lion with gold legs (KD) (NEW)","body_html":"<p>64x56x97 Silver Grey/Mink</p>","vendor":"Birbani","product_type":"","created_at":"2022-11-20T05:03:23-05:00","handle":"g-roma-chair-lion-with-gold-legs-kd-new","updated_at":"2023-10-23T22:28:20-04:00","published_at":"2022-11-20T05:03:23-05:00","template_suffix":null,"published_scope":"web","tags":"Chair","status":"active","admin_graphql_api_id":"gid://shopify/Product/7104150339637","variants":[{"id":41948289171509,"product_id":7104150339637,"title":"Default Title","price":"0.00","sku":null,"position":1,"inventory_policy":"deny","compare_at_price":null,"fulfillment_service":"manual","inventory_management":"shopify","option1":"Default Title","option2":null,"option3":null,"created_at":"2022-11-20T05:03:23-05:00","updated_at":"2023-10-23T22:28:20-04:00","taxable":true,"barcode":null,"grams":0,"weight":0,"weight_unit":"lb","inventory_item_id":44045568213045,"inventory_quantity":0,"old_inventory_quantity":0,"requires_shipping":true,"admin_graphql_api_id":"gid://shopify/ProductVariant/41948289171509","image_id":null}],"options":[{"id":9083580088373,"product_id":7104150339637,"name":"Title","position":1,"values":["Default Title"]}],"images":[],"image":null},{"id":7104151453749,"title":"Grey Marble Top & Stainless Steel","body_html":"<p>120x35x150 Grey</p>","vendor":"Birbani","product_type":"","created_at":"2022-11-20T05:03:48-05:00","handle":"grey-marble-top-stainless-steel","updated_at":"2023-10-23T22:28:26-04:00","published_at":"2022-11-20T05:03:48-05:00","template_suffix":null,"published_scope":"web","tags":"Bookshelf","status":"active","admin_graphql_api_id":"gid://shopify/Product/7104151453749","variants":[{"id":41948290285621,"product_id":7104151453749,"title":"Default Title","price":"0.00","sku":null,"position":1,"inventory_policy":"deny","compare_at_price":null,"fulfillment_service":"manual","inventory_management":"shopify","option1":"Default Title","option2":null,"option3":null,"created_at":"2022-11-20T05:03:48-05:00","updated_at":"2023-10-23T22:28:26-04:00","taxable":true,"barcode":null,"grams":0,"weight":0,"weight_unit":"lb","inventory_item_id":44045569327157,"inventory_quantity":0,"old_inventory_quantity":0,"requires_shipping":true,"admin_graphql_api_id":"gid://shopify/ProductVariant/41948290285621","image_id":null}],"options":[{"id":9083581202485,"product_id":7104151453749,"name":"Title","position":1,"values":["Default Title"]}],"images":[],"image":null},{"id":7104151879733,"title":"Half Moon Ext. Dining Table","body_html":"<p>92x75cm</p>","vendor":"Birbani","product_type":"","created_at":"2022-11-20T05:03:55-05:00","handle":"half-moon-ext-dining-table","updated_at":"2023-10-23T22:28:29-04:00","published_at":"2022-11-20T05:03:55-05:00","template_suffix":null,"published_scope":"web","tags":"Torino","status":"active","admin_graphql_api_id":"gid://shopify/Product/7104151879733","variants":[{"id":41948290711605,"product_id":7104151879733,"title":"Default Title","price":"0.00","sku":null,"position":1,"inventory_policy":"deny","compare_at_price":null,"fulfillment_service":"manual","inventory_management":"shopify","option1":"Default Title","option2":null,"option3":null,"created_at":"2022-11-20T05:03:56-05:00","updated_at":"2023-10-23T22:28:29-04:00","taxable":true,"barcode":null,"grams":0,"weight":0,"weight_unit":"kg","inventory_item_id":44045569753141,"inventory_quantity":0,"old_inventory_quantity":0,"requires_shipping":true,"admin_graphql_api_id":"gid://shopify/ProductVariant/41948290711605","image_id":null}],"options":[{"id":9083581628469,"product_id":7104151879733,"name":"Title","position":1,"values":["Default Title"]}],"images":[],"image":null},{"id":7104149946421,"title":"Jessica Chair ringer with chrome legs (KD)","body_html":"<p>55x55x95 Grey/Crushed Silver/Crushed Mink/Mink/Silver Grey/Black</p>","vendor":"Birbani","product_type":"","created_at":"2022-11-20T05:03:16-05:00","handle":"jessica-chair-ringer-with-chrome-legs-kd","updated_at":"2023-10-23T22:28:17-04:00","published_at":"2022-11-20T05:03:16-05:00","template_suffix":null,"published_scope":"web","tags":"Chair","status":"active","admin_graphql_api_id":"gid://shopify/Product/7104149946421","variants":[{"id":41948288778293,"product_id":7104149946421,"title":"Default Title","price":"0.00","sku":null,"position":1,"inventory_policy":"deny","compare_at_price":null,"fulfillment_service":"manual","inventory_management":"shopify","option1":"Default Title","option2":null,"option3":null,"created_at":"2022-11-20T05:03:16-05:00","updated_at":"2023-10-23T22:28:17-04:00","taxable":true,"barcode":null,"grams":0,"weight":0,"weight_unit":"lb","inventory_item_id":44045567819829,"inventory_quantity":0,"old_inventory_quantity":0,"requires_shipping":true,"admin_graphql_api_id":"gid://shopify/ProductVariant/41948288778293","image_id":null}],"options":[{"id":9083579695157,"product_id":7104149946421,"name":"Title","position":1,"values":["Default Title"]}],"images":[],"image":null},{"id":7104149913653,"title":"Jessica PU Chair ringer with chrome legs (KD) (NEW)","body_html":"<p>55x55x95 Grey</p>","vendor":"Birbani","product_type":"","created_at":"2022-11-20T05:03:15-05:00","handle":"jessica-pu-chair-ringer-with-chrome-legs-kd-new","updated_at":"2023-10-23T22:28:17-04:00","published_at":"2022-11-20T05:03:15-05:00","template_suffix":null,"published_scope":"web","tags":"Chair","status":"active","admin_graphql_api_id":"gid://shopify/Product/7104149913653","variants":[{"id":41948288745525,"product_id":7104149913653,"title":"Default Title","price":"0.00","sku":null,"position":1,"inventory_policy":"deny","compare_at_price":null,"fulfillment_service":"manual","inventory_management":"shopify","option1":"Default Title","option2":null,"option3":null,"created_at":"2022-11-20T05:03:15-05:00","updated_at":"2023-10-23T22:28:17-04:00","taxable":true,"barcode":null,"grams":0,"weight":0,"weight_unit":"kg","inventory_item_id":44045567787061,"inventory_quantity":0,"old_inventory_quantity":0,"requires_shipping":true,"admin_graphql_api_id":"gid://shopify/ProductVariant/41948288745525","image_id":null}],"options":[{"id":9083579662389,"product_id":7104149913653,"name":"Title","position":1,"values":["Default Title"]}],"images":[],"image":null},{"id":7104151224373,"title":"Lamp Table","body_html":"<p>50x50x55 Grey/Mixed Brown/Black/White</p>","vendor":"Birbani","product_type":"","created_at":"2022-11-20T05:03:43-05:00","handle":"lamp-table","updated_at":"2023-10-23T22:28:25-04:00","published_at":"2022-11-20T05:03:43-05:00","template_suffix":null,"published_scope":"web","tags":"Chelsea","status":"active","admin_graphql_api_id":"gid://shopify/Product/7104151224373","variants":[{"id":41948290056245,"product_id":7104151224373,"title":"Default Title","price":"0.00","sku":null,"position":1,"inventory_policy":"deny","compare_at_price":null,"fulfillment_service":"manual","inventory_management":"shopify","option1":"Default Title","option2":null,"option3":null,"created_at":"2022-11-20T05:03:43-05:00","updated_at":"2023-10-23T22:28:25-04:00","taxable":true,"barcode":null,"grams":0,"weight":0,"weight_unit":"lb","inventory_item_id":44045569097781,"inventory_quantity":0,"old_inventory_quantity":0,"requires_shipping":true,"admin_graphql_api_id":"gid://shopify/ProductVariant/41948290056245","image_id":null}],"options":[{"id":9083580973109,"product_id":7104151224373,"name":"Title","position":1,"values":["Default Title"]}],"images":[],"image":null},{"id":7104150962229,"title":"Lamp Table (NEW)","body_html":"<p>50x50x55 Kata Gold Ceramic</p>","vendor":"Birbani","product_type":"","created_at":"2022-11-20T05:03:38-05:00","handle":"lamp-table-new","updated_at":"2023-10-23T22:28:23-04:00","published_at":"2022-11-20T05:03:38-05:00","template_suffix":null,"published_scope":"web","tags":"G-Lewis","status":"active","admin_graphql_api_id":"gid://shopify/Product/7104150962229","variants":[{"id":41948289794101,"product_id":7104150962229,"title":"Default Title","price":"0.00","sku":null,"position":1,"inventory_policy":"deny","compare_at_price":null,"fulfillment_service":"manual","inventory_management":"shopify","option1":"Default Title","option2":null,"option3":null,"created_at":"2022-11-20T05:03:38-05:00","updated_at":"2023-10-23T22:28:23-04:00","taxable":true,"barcode":null,"grams":0,"weight":0,"weight_unit":"lb","inventory_item_id":44045568835637,"inventory_quantity":0,"old_inventory_quantity":0,"requires_shipping":true,"admin_graphql_api_id":"gid://shopify/ProductVariant/41948289794101","image_id":null}],"options":[{"id":9083580710965,"product_id":7104150962229,"name":"Title","position":1,"values":["Default Title"]}],"images":[],"image":null},{"id":7104150798389,"title":"Lamp Table H/L (NEW)","body_html":"<p>50x59/55x49 Black Legs Kata Gold Ceramic</p>","vendor":"Birbani","product_type":"","created_at":"2022-11-20T05:03:33-05:00","handle":"lamp-table-h-l-new","updated_at":"2023-10-23T22:28:22-04:00","published_at":"2022-11-20T05:03:32-05:00","template_suffix":null,"published_scope":"web","tags":"Venice","status":"active","admin_graphql_api_id":"gid://shopify/Product/7104150798389","variants":[{"id":41948289630261,"product_id":7104150798389,"title":"Default Title","price":"0.00","sku":null,"position":1,"inventory_policy":"deny","compare_at_price":null,"fulfillment_service":"manual","inventory_management":"shopify","option1":"Default Title","option2":null,"option3":null,"created_at":"2022-11-20T05:03:33-05:00","updated_at":"2023-10-23T22:28:22-04:00","taxable":true,"barcode":null,"grams":0,"weight":0,"weight_unit":"lb","inventory_item_id":44045568671797,"inventory_quantity":0,"old_inventory_quantity":0,"requires_shipping":true,"admin_graphql_api_id":"gid://shopify/ProductVariant/41948289630261","image_id":null}],"options":[{"id":9083580547125,"product_id":7104150798389,"name":"Title","position":1,"values":["Default Title"]}],"images":[],"image":null},{"id":7104152305717,"title":"Large Bookcase","body_html":"<p>80x32x180</p>","vendor":"Birbani","product_type":"","created_at":"2022-11-20T05:04:03-05:00","handle":"large-bookcase","updated_at":"2023-10-23T22:28:31-04:00","published_at":"2022-11-20T05:04:03-05:00","template_suffix":null,"published_scope":"web","tags":"Torino/Lucca","status":"active","admin_graphql_api_id":"gid://shopify/Product/7104152305717","variants":[{"id":41948291137589,"product_id":7104152305717,"title":"Default Title","price":"0.00","sku":null,"position":1,"inventory_policy":"deny","compare_at_price":null,"fulfillment_service":"manual","inventory_management":"shopify","option1":"Default Title","option2":null,"option3":null,"created_at":"2022-11-20T05:04:03-05:00","updated_at":"2023-10-23T22:28:31-04:00","taxable":true,"barcode":null,"grams":0,"weight":0,"weight_unit":"kg","inventory_item_id":44045570179125,"inventory_quantity":0,"old_inventory_quantity":0,"requires_shipping":true,"admin_graphql_api_id":"gid://shopify/ProductVariant/41948291137589","image_id":null}],"options":[{"id":9083582054453,"product_id":7104152305717,"name":"Title","position":1,"values":["Default Title"]}],"images":[],"image":null},{"id":7104152993845,"title":"Large Sideboard","body_html":"<p>160x40x70</p>","vendor":"Birbani","product_type":"","created_at":"2022-11-20T05:04:15-05:00","handle":"large-sideboard","updated_at":"2023-10-23T22:28:35-04:00","published_at":"2022-11-20T05:04:15-05:00","template_suffix":null,"published_scope":"web","tags":"Milan","status":"active","admin_graphql_api_id":"gid://shopify/Product/7104152993845","variants":[{"id":41948291825717,"product_id":7104152993845,"title":"Default Title","price":"0.00","sku":null,"position":1,"inventory_policy":"deny","compare_at_price":null,"fulfillment_service":"manual","inventory_management":"shopify","option1":"Default Title","option2":null,"option3":null,"created_at":"2022-11-20T05:04:15-05:00","updated_at":"2023-10-23T22:28:35-04:00","taxable":true,"barcode":null,"grams":0,"weight":0,"weight_unit":"kg","inventory_item_id":44045570867253,"inventory_quantity":0,"old_inventory_quantity":0,"requires_shipping":true,"admin_graphql_api_id":"gid://shopify/ProductVariant/41948291825717","image_id":null}],"options":[{"id":9083582742581,"product_id":7104152993845,"name":"Title","position":1,"values":["Default Title"]}],"images":[],"image":null},{"id":7104151978037,"title":"Large Sideboard 3 Doors 3 Drawers","body_html":"<p>137x40x81</p>","vendor":"Birbani","product_type":"","created_at":"2022-11-20T05:03:57-05:00","handle":"large-sideboard-3-doors-3-drawers","updated_at":"2023-10-23T22:28:29-04:00","published_at":"2022-11-20T05:03:57-05:00","template_suffix":null,"published_scope":"web","tags":"Torino/Lucca","status":"active","admin_graphql_api_id":"gid://shopify/Product/7104151978037","variants":[{"id":41948290809909,"product_id":7104151978037,"title":"Default Title","price":"0.00","sku":null,"position":1,"inventory_policy":"deny","compare_at_price":null,"fulfillment_service":"manual","inventory_management":"shopify","option1":"Default Title","option2":null,"option3":null,"created_at":"2022-11-20T05:03:57-05:00","updated_at":"2023-10-23T22:28:29-04:00","taxable":true,"barcode":null,"grams":0,"weight":0,"weight_unit":"kg","inventory_item_id":44045569851445,"inventory_quantity":0,"old_inventory_quantity":0,"requires_shipping":true,"admin_graphql_api_id":"gid://shopify/ProductVariant/41948290809909","image_id":null}],"options":[{"id":9083581726773,"product_id":7104151978037,"name":"Title","position":1,"values":["Default Title"]}],"images":[],"image":null},{"id":7104152928309,"title":"Large TV Cabinet","body_html":"<p>160x40x45</p>","vendor":"Birbani","product_type":"","created_at":"2022-11-20T05:04:14-05:00","handle":"large-tv-cabinet","updated_at":"2023-10-23T22:28:35-04:00","published_at":"2022-11-20T05:04:13-05:00","template_suffix":null,"published_scope":"web","tags":"Milan","status":"active","admin_graphql_api_id":"gid://shopify/Product/7104152928309","variants":[{"id":41948291760181,"product_id":7104152928309,"title":"Default Title","price":"0.00","sku":null,"position":1,"inventory_policy":"deny","compare_at_price":null,"fulfillment_service":"manual","inventory_management":"shopify","option1":"Default Title","option2":null,"option3":null,"created_at":"2022-11-20T05:04:14-05:00","updated_at":"2023-10-23T22:28:35-04:00","taxable":true,"barcode":null,"grams":0,"weight":0,"weight_unit":"kg","inventory_item_id":44045570801717,"inventory_quantity":0,"old_inventory_quantity":0,"requires_shipping":true,"admin_graphql_api_id":"gid://shopify/ProductVariant/41948291760181","image_id":null}],"options":[{"id":9083582677045,"product_id":7104152928309,"name":"Title","position":1,"values":["Default Title"]}],"images":[],"image":null},{"id":7104152207413,"title":"Large TV Unit","body_html":"<p>120x37x50</p>","vendor":"Birbani","product_type":"","created_at":"2022-11-20T05:04:01-05:00","handle":"large-tv-unit","updated_at":"2023-10-23T22:28:31-04:00","published_at":"2022-11-20T05:04:01-05:00","template_suffix":null,"published_scope":"web","tags":"Torino/Lucca","status":"active","admin_graphql_api_id":"gid://shopify/Product/7104152207413","variants":[{"id":41948291039285,"product_id":7104152207413,"title":"Default Title","price":"0.00","sku":null,"position":1,"inventory_policy":"deny","compare_at_price":null,"fulfillment_service":"manual","inventory_management":"shopify","option1":"Default Title","option2":null,"option3":null,"created_at":"2022-11-20T05:04:01-05:00","updated_at":"2023-10-23T22:28:31-04:00","taxable":true,"barcode":null,"grams":0,"weight":0,"weight_unit":"kg","inventory_item_id":44045570080821,"inventory_quantity":0,"old_inventory_quantity":0,"requires_shipping":true,"admin_graphql_api_id":"gid://shopify/ProductVariant/41948291039285","image_id":null}],"options":[{"id":9083581956149,"product_id":7104152207413,"name":"Title","position":1,"values":["Default Title"]}],"images":[],"image":null}]